CONTRIBUTING.rst
HISTORY.rst
LICENSE
MANIFEST.in
README.rst
setup.cfg
setup.py
aquaman/__init__.py
aquaman/aquaman.py
aquaman.egg-info/PKG-INFO
aquaman.egg-info/SOURCES.txt
aquaman.egg-info/dependency_links.txt
aquaman.egg-info/top_level.txt
docs/Makefile
docs/conf.py
docs/contributing.rst
docs/history.rst
docs/index.rst
docs/installation.rst
docs/make.bat
docs/readme.rst
docs/usage.rst
tests/__init__.py
tests/test_aquaman.py