Metadata-Version: 1.1
Name: aquaman
Version: 0.0.1
Summary: aquaman
Home-page: UNKNOWN
Author: Jaewon Chung
Author-email: j1c@jhu.edu
License: Apache Software License 2.0
Keywords: aquaman
Platform: UNKNOWN
Classifier: Development Status :: 2 - Pre-Alpha
Classifier: Intended Audience :: Developers
Classifier: License :: OSI Approved :: Apache Software License
Classifier: Natural Language :: English
Classifier: Programming Language :: Python :: 3.6
Classifier: Programming Language :: Python :: 3.7
